roadtraffic/__init__.py
roadtraffic/fintraffic.py
roadtraffic/py.typed
roadtraffic/traffic_data_classes/__init__.py
roadtraffic/traffic_data_classes/aggregated_data.py
roadtraffic/traffic_data_classes/bagged_data.py
roadtraffic/traffic_data_classes/raw_data.py
roadtraffic/utils/__init__.py
roadtraffic/utils/constants.py
roadtraffic/utils/funcs.py
roadtraffic/utils/load.py
roadtraffic/utils/models.py
roadtraffic/utils/process.py
roadtraffic-1.0.0.dist-info/LICENSE
roadtraffic-1.0.0.dist-info/METADATA
roadtraffic-1.0.0.dist-info/WHEEL
roadtraffic-1.0.0.dist-info/top_level.txt
roadtraffic-1.0.0.dist-info/RECORD
