Metadata-Version: 2.1
Name: roadtraffic
Version: 1.0.0
Summary: A package for road traffic data analysis
Home-page: https://github.com/iarokr/roadtraffic
Download-URL: https://pypi.org/project/roadtraffic/
Author: Iaroslav Kriuchkov
Author-email: "Iaroslav Kriuchkov, Timo Kuosmanen" <iaroslav.kriuchkov@aalto.fi>
Maintainer-email: Iaroslav Kriuchkov <iaroslav.kriuchkov@aalto.fi>
License: GNU General Public License v3 (GPLv3)
Project-URL: repository, https://github.com/iarokr/roadtraffic
Project-URL: changelog, https://github.com/iarokr/roadtraffic/blob/main/CHANGELOG.md
Keywords: road traffic,data analysis,convex regression,quantile regression
Classifier: Development Status :: 5 - Production/Stable
Classifier: Intended Audience :: Developers
Classifier: Intended Audience :: Science/Research
Classifier: License :: OSI Approved :: GNU General Public License v3 (GPLv3)
Classifier: Operating System :: OS Independent
Classifier: Programming Language :: Python :: 3
Classifier: Programming Language :: Python :: 3.9
Classifier: Programming Language :: Python :: 3.10
Classifier: Programming Language :: Python :: 3.11
Classifier: Programming Language :: Python :: 3.12
Classifier: Programming Language :: Python :: 3 :: Only
Classifier: Topic :: Software Development :: Libraries :: Python Modules
Requires-Python: >=3.8, <4
License-File: LICENSE
Requires-Dist: numpy >=1.26
Requires-Dist: pandas >=2.0
Requires-Dist: tqdm >=4.66
Requires-Dist: scipy >=1.11
Requires-Dist: pystoned >=0.6.6
Requires-Dist: requests >=2.31
Requires-Dist: urllib3 ==1.26.6
Requires-Dist: pandas-stubs >=2.1.1
Provides-Extra: test
Requires-Dist: flake8 >=6.1.0 ; extra == 'test'
Requires-Dist: tox >=4.11.0 ; extra == 'test'
Requires-Dist: pytest >=7.4.0 ; extra == 'test'
Requires-Dist: pytest-cov >=4.0.0 ; extra == 'test'
Requires-Dist: mypy >=1.7.0 ; extra == 'test'
